pyonvista/__init__.py
pyonvista/api.py
pyonvista/util.py
pyonvista-0.8.4.dist-info/licenses/LICENSE.md
pyonvista-0.8.4.dist-info/METADATA
pyonvista-0.8.4.dist-info/WHEEL
pyonvista-0.8.4.dist-info/top_level.txt
pyonvista-0.8.4.dist-info/RECORD
