Metadata-Version: 2.4
Name: pyonvista
Version: 0.8.4
Summary: A tiny python API wrapper for onvista.de financial website.
Author-email: Simon Bauer <seimen@cloasdata.de>
License-Expression: MIT
Project-URL: Homepage, https://github.com/cloasdata/pyonvista
Classifier: Programming Language :: Python :: 3
Classifier: Operating System :: OS Independent
Requires-Python: >=3.10
License-File: LICENSE.md
Requires-Dist: aiohttp>=3.8.1
Provides-Extra: test
Requires-Dist: pytest>=7.0.0; extra == "test"
Dynamic: license-file
